efficientnet_pytorch/__init__.py
efficientnet_pytorch/model.py
efficientnet_pytorch/utils.py
efficientnet_pytorch-0.3.0.dist-info/LICENSE
efficientnet_pytorch-0.3.0.dist-info/METADATA
efficientnet_pytorch-0.3.0.dist-info/WHEEL
efficientnet_pytorch-0.3.0.dist-info/top_level.txt
efficientnet_pytorch-0.3.0.dist-info/RECORD
