Metadata-Version: 2.1
Name: efficientnet-pytorch
Version: 0.3.0
Summary: EfficientNet implemented in PyTorch.
Home-page: https://github.com/lukemelas/efficientnet_pytorch
Author: Luke
Author-email: lmelaskyriazi@college.harvard.edu
License: Apache
Platform: UNKNOWN
Classifier: License :: OSI Approved :: Apache Software License
Classifier: Programming Language :: Python
Classifier: Programming Language :: Python :: 3
Classifier: Programming Language :: Python :: 3.6
Requires-Python: >=3.5.0
Requires-Dist: torch
